http_constants/__init__.py
http_constants/headers.py
http_constants/status.py
http_constants-0.4.0.dist-info/LICENSE
http_constants-0.4.0.dist-info/METADATA
http_constants-0.4.0.dist-info/WHEEL
http_constants-0.4.0.dist-info/top_level.txt
http_constants-0.4.0.dist-info/RECORD
